freegames/__init__.py
freegames/__main__.py
freegames/ant.py
freegames/avoid.py
freegames/bagels.py
freegames/bounce.py
freegames/cannon.py
freegames/car.gif
freegames/connect.py
freegames/crypto.py
freegames/fidget.py
freegames/flappy.py
freegames/guess.py
freegames/illusion.py
freegames/life.py
freegames/madlibs.py
freegames/maze.py
freegames/memory.py
freegames/minesweeper.py
freegames/pacman.py
freegames/paint.py
freegames/pong.py
freegames/rps.py
freegames/simonsays.py
freegames/snake.py
freegames/tictactoe.py
freegames/tiles.py
freegames/tron.py
freegames/typing.py
freegames/utils.py
freegames-2.5.2.dist-info/LICENSE
freegames-2.5.2.dist-info/METADATA
freegames-2.5.2.dist-info/WHEEL
freegames-2.5.2.dist-info/top_level.txt
freegames-2.5.2.dist-info/RECORD
