Metadata-Version: 2.1
Name: freegames
Version: 2.5.2
Summary: Free Python Games
Author-email: Grant Jenks <contact@grantjenks.com>
License: Apache 2.0
Project-URL: Documentation, https://grantjenks.com/docs/freegames/
Project-URL: Funding, https://gum.co/freegames
Project-URL: Source, https://github.com/grantjenks/free-python-games
Project-URL: Tracker, https://github.com/grantjenks/django-codemirror6/issues
Keywords: free,games
Classifier: Development Status :: 5 - Production/Stable
Classifier: Intended Audience :: Education
Classifier: Intended Audience :: End Users/Desktop
Classifier: License :: OSI Approved :: Apache Software License
Classifier: Natural Language :: English
Classifier: Programming Language :: Python
Classifier: Programming Language :: Python :: 3
Classifier: Topic :: Games/Entertainment
Classifier: Topic :: Games/Entertainment :: Arcade
Classifier: Topic :: Games/Entertainment :: Board Games
Classifier: Topic :: Games/Entertainment :: Puzzle Games
Classifier: Topic :: Games/Entertainment :: Side-Scrolling/Arcade Games
Classifier: Topic :: Games/Entertainment :: Simulation
Classifier: Topic :: Games/Entertainment :: Turn Based Strategy
Requires-Python: >=3.7
License-File: LICENSE
